{
  "clientLibrary": {
    "apis": [
      {
        "id": "google.cloud.servicedirectory.v1beta1",
        "version": "v1beta1"
      }
    ],
    "language": "GO",
    "name": "cloud.google.com/go/servicedirectory/apiv1beta1",
    "version": "1.14.0"
  },
  "snippets": [
    {
      "clientMethod": {
        "client": {
          "fullName": "google.cloud.servicedirectory.v1beta1.LookupClient",
          "shortName": "LookupClient"
        },
        "fullName": "google.cloud.servicedirectory.v1beta1.LookupClient.GetLocation",
        "method": {
          "fullName": "google.cloud.location.Locations.GetLocation",
          "service": {
            "fullName": "google.cloud.location.Locations",
            "shortName": "Locations"
          },
          "shortName": "GetLocation"
        },
        "parameters": [
          {
            "name": "ctx",
            "type": "context.Context"
          },
          {
            "name": "req",
            "type": "locationpb.GetLocationRequest"
          },
          {
            "name": "opts",
            "type": "...gax.CallOption"
          }
        ],
        "resultType": "*locationpb.Location",
        "shortName": "GetLocation"
      },
      "description": "GetLocation gets information about a location.",
      "file": "LookupClient/GetLocation/main.go",
      "language": "GO",
      "origin": "API_DEFINITION",
      "regionTag": "servicedirectory_v1beta1_generated_LookupService_GetLocation_sync",
      "segments": [
        {
          "end": 53,
          "start": 18,
          "type": "FULL"
        }
      ],
      "title": "servicedirectory GetLocation Sample"
    },
    {
      "clientMethod": {
        "client": {
          "fullName": "google.cloud.servicedirectory.v1beta1.LookupClient",
          "shortName": "LookupClient"
        },
        "fullName": "google.cloud.servicedirectory.v1beta1.LookupClient.ListLocations",
        "method": {
          "fullName": "google.cloud.location.Locations.ListLocations",
          "service": {
            "fullName": "google.cloud.location.Locations",
            "shortName": "Locations"
          },
          "shortName": "ListLocations"
        },
        "parameters": [
          {
            "name": "ctx",
            "type": "context.Context"
          },
          {
            "name": "req",
            "type": "locationpb.ListLocationsRequest"
          },
          {
            "name": "opts",
            "type": "...gax.CallOption"
          }
        ],
        "resultType": "LocationIterator",
        "shortName": "ListLocations"
      },
      "description": "ListLocations lists information about the supported locations for this service.",
      "file": "LookupClient/ListLocations/main.go",
      "language": "GO",
      "origin": "API_DEFINITION",
      "regionTag": "servicedirectory_v1beta1_generated_LookupService_ListLocations_sync",
      "segments": [
        {
          "end": 66,
          "start": 18,
          "type": "FULL"
        }
      ],
      "title": "servicedirectory ListLocations Sample"
    },
    {
      "clientMethod": {
        "client": {
          "fullName": "google.cloud.servicedirectory.v1beta1.LookupClient",
          "shortName": "LookupClient"
        },
        "fullName": "google.cloud.servicedirectory.v1beta1.LookupClient.ResolveService",
        "method": {
          "fullName": "google.cloud.servicedirectory.v1beta1.LookupService.ResolveService",
          "service": {
            "fullName": "google.cloud.servicedirectory.v1beta1.LookupService",
            "shortName": "LookupService"
          },
          "shortName": "ResolveService"
        },
        "parameters": [
          {
            "name": "ctx",
            "type": "context.Context"
          },
          {
            "name": "req",
            "type": "servicedirectorypb.ResolveServiceRequest"
          },
          {
            "name": "opts",
            "type": "...gax.CallOption"
          }
        ],
        "resultType": "*servicedirectorypb.ResolveServiceResponse",
        "shortName": "ResolveService"
      },
      "description": "ResolveService returns a [service][google.cloud.servicedirectory.v1beta1.Service] and its\nassociated endpoints.\nResolving a service is not considered an active developer method.",
      "file": "LookupClient/ResolveService/main.go",
      "language": "GO",
      "origin": "API_DEFINITION",
      "regionTag": "servicedirectory_v1beta1_generated_LookupService_ResolveService_sync",
      "segments": [
        {
          "end": 53,
          "start": 18,
          "type": "FULL"
        }
      ],
      "title": "servicedirectory ResolveService Sample"
    },
    {
      "clientMethod": {
        "client": {
          "fullName": "google.cloud.servicedirectory.v1beta1.RegistrationClient",
          "shortName": "RegistrationClient"
        },
        "fullName": "google.cloud.servicedirectory.v1beta1.RegistrationClient.CreateEndpoint",
        "method": {
          "fullName": "google.cloud.servicedirectory.v1beta1.RegistrationService.CreateEndpoint",
          "service": {
            "fullName": "google.cloud.servicedirectory.v1beta1.RegistrationService",
            "shortName": "RegistrationService"
          },
          "shortName": "CreateEndpoint"
        },
        "parameters": [
          {
            "name": "ctx",
            "type": "context.Context"
          },
          {
            "name": "req",
            "type": "servicedirectorypb.CreateEndpointRequest"
          },
          {
            "name": "opts",
            "type": "...gax.CallOption"
          }
        ],
        "resultType": "*servicedirectorypb.Endpoint",
        "shortName": "CreateEndpoint"
      },
      "description": "CreateEndpoint creates an endpoint, and returns the new endpoint.",
      "file": "RegistrationClient/CreateEndpoint/main.go",
      "language": "GO",
      "origin": "API_DEFINITION",
      "regionTag": "servicedirectory_v1beta1_generated_RegistrationService_CreateEndpoint_sync",
      "segments": [
        {
          "end": 53,
          "start": 18,
          "type": "FULL"
        }
      ],
      "title": "servicedirectory CreateEndpoint Sample"
    },
    {
      "clientMethod": {
        "client": {
          "fullName": "google.cloud.servicedirectory.v1beta1.RegistrationClient",
          "shortName": "RegistrationClient"
        },
        "fullName": "google.cloud.servicedirectory.v1beta1.RegistrationClient.CreateNamespace",
        "method": {
          "fullName": "google.cloud.servicedirectory.v1beta1.RegistrationService.CreateNamespace",
          "service": {
            "fullName": "google.cloud.servicedirectory.v1beta1.RegistrationService",
            "shortName": "RegistrationService"
          },
          "shortName": "CreateNamespace"
        },
        "parameters": [
          {
            "name": "ctx",
            "type": "context.Context"
          },
          {
            "name": "req",
            "type": "servicedirectorypb.CreateNamespaceRequest"
          },
          {
            "name": "opts",
            "type": "...gax.CallOption"
          }
        ],
        "resultType": "*servicedirectorypb.Namespace",
        "shortName": "CreateNamespace"
      },
      "description": "CreateNamespace creates a namespace, and returns the new namespace.",
      "file": "RegistrationClient/CreateNamespace/main.go",
      "language": "GO",
      "origin": "API_DEFINITION",
      "regionTag": "servicedirectory_v1beta1_generated_RegistrationService_CreateNamespace_sync",
      "segments": [
        {
          "end": 53,
          "start": 18,
          "type": "FULL"
        }
      ],
      "title": "servicedirectory CreateNamespace Sample"
    },
    {
      "clientMethod": {
        "client": {
          "fullName": "google.cloud.servicedirectory.v1beta1.RegistrationClient",
          "shortName": "RegistrationClient"
        },
        "fullName": "google.cloud.servicedirectory.v1beta1.RegistrationClient.CreateService",
        "method": {
          "fullName": "google.cloud.servicedirectory.v1beta1.RegistrationService.CreateService",
          "service": {
            "fullName": "google.cloud.servicedirectory.v1beta1.RegistrationService",
            "shortName": "RegistrationService"
          },
          "shortName": "CreateService"
        },
        "parameters": [
          {
            "name": "ctx",
            "type": "context.Context"
          },
          {
            "name": "req",
            "type": "servicedirectorypb.CreateServiceRequest"
          },
          {
            "name": "opts",
            "type": "...gax.CallOption"
          }
        ],
        "resultType": "*servicedirectorypb.Service",
        "shortName": "CreateService"
      },
      "description": "CreateService creates a service, and returns the new service.",
      "file": "RegistrationClient/CreateService/main.go",
      "language": "GO",
      "origin": "API_DEFINITION",
      "regionTag": "servicedirectory_v1beta1_generated_RegistrationService_CreateService_sync",
      "segments": [
        {
          "end": 53,
          "start": 18,
          "type": "FULL"
        }
      ],
      "title": "servicedirectory CreateService Sample"
    },
    {
      "clientMethod": {
        "client": {
          "fullName": "google.cloud.servicedirectory.v1beta1.RegistrationClient",
          "shortName": "RegistrationClient"
        },
        "fullName": "google.cloud.servicedirectory.v1beta1.RegistrationClient.DeleteEndpoint",
        "method": {
          "fullName": "google.cloud.servicedirectory.v1beta1.RegistrationService.DeleteEndpoint",
          "service": {
            "fullName": "google.cloud.servicedirectory.v1beta1.RegistrationService",
            "shortName": "RegistrationService"
          },
          "shortName": "DeleteEndpoint"
        },
        "parameters": [
          {
            "name": "ctx",
            "type": "context.Context"
          },
          {
            "name": "req",
            "type": "servicedirectorypb.DeleteEndpointRequest"
          },
          {
            "name": "opts",
            "type": "...gax.CallOption"
          }
        ],
        "shortName": "DeleteEndpoint"
      },
      "description": "DeleteEndpoint deletes an endpoint.",
      "file": "RegistrationClient/DeleteEndpoint/main.go",
      "language": "GO",
      "origin": "API_DEFINITION",
      "regionTag": "servicedirectory_v1beta1_generated_RegistrationService_DeleteEndpoint_sync",
      "segments": [
        {
          "end": 51,
          "start": 18,
          "type": "FULL"
        }
      ],
      "title": "servicedirectory DeleteEndpoint Sample"
    },
    {
      "clientMethod": {
        "client": {
          "fullName": "google.cloud.servicedirectory.v1beta1.RegistrationClient",
          "shortName": "RegistrationClient"
        },
        "fullName": "google.cloud.servicedirectory.v1beta1.RegistrationClient.DeleteNamespace",
        "method": {
          "fullName": "google.cloud.servicedirectory.v1beta1.RegistrationService.DeleteNamespace",
          "service": {
            "fullName": "google.cloud.servicedirectory.v1beta1.RegistrationService",
            "shortName": "RegistrationService"
          },
          "shortName": "DeleteNamespace"
        },
        "parameters": [
          {
            "name": "ctx",
            "type": "context.Context"
          },
          {
            "name": "req",
            "type": "servicedirectorypb.DeleteNamespaceRequest"
          },
          {
            "name": "opts",
            "type": "...gax.CallOption"
          }
        ],
        "shortName": "DeleteNamespace"
      },
      "description": "DeleteNamespace deletes a namespace. This also deletes all services and endpoints in\nthe namespace.",
      "file": "RegistrationClient/DeleteNamespace/main.go",
      "language": "GO",
      "origin": "API_DEFINITION",
      "regionTag": "servicedirectory_v1beta1_generated_RegistrationService_DeleteNamespace_sync",
      "segments": [
        {
          "end": 51,
          "start": 18,
          "type": "FULL"
        }
      ],
      "title": "servicedirectory DeleteNamespace Sample"
    },
    {
      "clientMethod": {
        "client": {
          "fullName": "google.cloud.servicedirectory.v1beta1.RegistrationClient",
          "shortName": "RegistrationClient"
        },
        "fullName": "google.cloud.servicedirectory.v1beta1.RegistrationClient.DeleteService",
        "method": {
          "fullName": "google.cloud.servicedirectory.v1beta1.RegistrationService.DeleteService",
          "service": {
            "fullName": "google.cloud.servicedirectory.v1beta1.RegistrationService",
            "shortName": "RegistrationService"
          },
          "shortName": "DeleteService"
        },
        "parameters": [
          {
            "name": "ctx",
            "type": "context.Context"
          },
          {
            "name": "req",
            "type": "servicedirectorypb.DeleteServiceRequest"
          },
          {
            "name": "opts",
            "type": "...gax.CallOption"
          }
        ],
        "shortName": "DeleteService"
      },
      "description": "DeleteService deletes a service. This also deletes all endpoints associated with\nthe service.",
      "file": "RegistrationClient/DeleteService/main.go",
      "language": "GO",
      "origin": "API_DEFINITION",
      "regionTag": "servicedirectory_v1beta1_generated_RegistrationService_DeleteService_sync",
      "segments": [
        {
          "end": 51,
          "start": 18,
          "type": "FULL"
        }
      ],
      "title": "servicedirectory DeleteService Sample"
    },
    {
      "clientMethod": {
        "client": {
          "fullName": "google.cloud.servicedirectory.v1beta1.RegistrationClient",
          "shortName": "RegistrationClient"
        },
        "fullName": "google.cloud.servicedirectory.v1beta1.RegistrationClient.GetEndpoint",
        "method": {
          "fullName": "google.cloud.servicedirectory.v1beta1.RegistrationService.GetEndpoint",
          "service": {
            "fullName": "google.cloud.servicedirectory.v1beta1.RegistrationService",
            "shortName": "RegistrationService"
          },
          "shortName": "GetEndpoint"
        },
        "parameters": [
          {
            "name": "ctx",
            "type": "context.Context"
          },
          {
            "name": "req",
            "type": "servicedirectorypb.GetEndpointRequest"
          },
          {
            "name": "opts",
            "type": "...gax.CallOption"
          }
        ],
        "resultType": "*servicedirectorypb.Endpoint",
        "shortName": "GetEndpoint"
      },
      "description": "GetEndpoint gets an endpoint.",
      "file": "RegistrationClient/GetEndpoint/main.go",
      "language": "GO",
      "origin": "API_DEFINITION",
      "regionTag": "servicedirectory_v1beta1_generated_RegistrationService_GetEndpoint_sync",
      "segments": [
        {
          "end": 53,
          "start": 18,
          "type": "FULL"
        }
      ],
      "title": "servicedirectory GetEndpoint Sample"
    },
    {
      "clientMethod": {
        "client": {
          "fullName": "google.cloud.servicedirectory.v1beta1.RegistrationClient",
          "shortName": "RegistrationClient"
        },
        "fullName": "google.cloud.servicedirectory.v1beta1.RegistrationClient.GetIamPolicy",
        "method": {
          "fullName": "google.cloud.servicedirectory.v1beta1.RegistrationService.GetIamPolicy",
          "service": {
            "fullName": "google.cloud.servicedirectory.v1beta1.RegistrationService",
            "shortName": "RegistrationService"
          },
          "shortName": "GetIamPolicy"
        },
        "parameters": [
          {
            "name": "ctx",
            "type": "context.Context"
          },
          {
            "name": "req",
            "type": "iampb.GetIamPolicyRequest"
          },
          {
            "name": "opts",
            "type": "...gax.CallOption"
          }
        ],
        "resultType": "*iampb.Policy",
        "shortName": "GetIamPolicy"
      },
      "description": "GetIamPolicy gets the IAM Policy for a resource",
      "file": "RegistrationClient/GetIamPolicy/main.go",
      "language": "GO",
      "origin": "API_DEFINITION",
      "regionTag": "servicedirectory_v1beta1_generated_RegistrationService_GetIamPolicy_sync",
      "segments": [
        {
          "end": 53,
          "start": 18,
          "type": "FULL"
        }
      ],
      "title": "servicedirectory GetIamPolicy Sample"
    },
    {
      "clientMethod": {
        "client": {
          "fullName": "google.cloud.servicedirectory.v1beta1.RegistrationClient",
          "shortName": "RegistrationClient"
        },
        "fullName": "google.cloud.servicedirectory.v1beta1.RegistrationClient.GetLocation",
        "method": {
          "fullName": "google.cloud.location.Locations.GetLocation",
          "service": {
            "fullName": "google.cloud.location.Locations",
            "shortName": "Locations"
          },
          "shortName": "GetLocation"
        },
        "parameters": [
          {
            "name": "ctx",
            "type": "context.Context"
          },
          {
            "name": "req",
            "type": "locationpb.GetLocationRequest"
          },
          {
            "name": "opts",
            "type": "...gax.CallOption"
          }
        ],
        "resultType": "*locationpb.Location",
        "shortName": "GetLocation"
      },
      "description": "GetLocation gets information about a location.",
      "file": "RegistrationClient/GetLocation/main.go",
      "language": "GO",
      "origin": "API_DEFINITION",
      "regionTag": "servicedirectory_v1beta1_generated_RegistrationService_GetLocation_sync",
      "segments": [
        {
          "end": 53,
          "start": 18,
          "type": "FULL"
        }
      ],
      "title": "servicedirectory GetLocation Sample"
    },
    {
      "clientMethod": {
        "client": {
          "fullName": "google.cloud.servicedirectory.v1beta1.RegistrationClient",
          "shortName": "RegistrationClient"
        },
        "fullName": "google.cloud.servicedirectory.v1beta1.RegistrationClient.GetNamespace",
        "method": {
          "fullName": "google.cloud.servicedirectory.v1beta1.RegistrationService.GetNamespace",
          "service": {
            "fullName": "google.cloud.servicedirectory.v1beta1.RegistrationService",
            "shortName": "RegistrationService"
          },
          "shortName": "GetNamespace"
        },
        "parameters": [
          {
            "name": "ctx",
            "type": "context.Context"
          },
          {
            "name": "req",
            "type": "servicedirectorypb.GetNamespaceRequest"
          },
          {
            "name": "opts",
            "type": "...gax.CallOption"
          }
        ],
        "resultType": "*servicedirectorypb.Namespace",
        "shortName": "GetNamespace"
      },
      "description": "GetNamespace gets a namespace.",
      "file": "RegistrationClient/GetNamespace/main.go",
      "language": "GO",
      "origin": "API_DEFINITION",
      "regionTag": "servicedirectory_v1beta1_generated_RegistrationService_GetNamespace_sync",
      "segments": [
        {
          "end": 53,
          "start": 18,
          "type": "FULL"
        }
      ],
      "title": "servicedirectory GetNamespace Sample"
    },
    {
      "clientMethod": {
        "client": {
          "fullName": "google.cloud.servicedirectory.v1beta1.RegistrationClient",
          "shortName": "RegistrationClient"
        },
        "fullName": "google.cloud.servicedirectory.v1beta1.RegistrationClient.GetService",
        "method": {
          "fullName": "google.cloud.servicedirectory.v1beta1.RegistrationService.GetService",
          "service": {
            "fullName": "google.cloud.servicedirectory.v1beta1.RegistrationService",
            "shortName": "RegistrationService"
          },
          "shortName": "GetService"
        },
        "parameters": [
          {
            "name": "ctx",
            "type": "context.Context"
          },
          {
            "name": "req",
            "type": "servicedirectorypb.GetServiceRequest"
          },
          {
            "name": "opts",
            "type": "...gax.CallOption"
          }
        ],
        "resultType": "*servicedirectorypb.Service",
        "shortName": "GetService"
      },
      "description": "GetService gets a service.",
      "file": "RegistrationClient/GetService/main.go",
      "language": "GO",
      "origin": "API_DEFINITION",
      "regionTag": "servicedirectory_v1beta1_generated_RegistrationService_GetService_sync",
      "segments": [
        {
          "end": 53,
          "start": 18,
          "type": "FULL"
        }
      ],
      "title": "servicedirectory GetService Sample"
    },
    {
      "clientMethod": {
        "client": {
          "fullName": "google.cloud.servicedirectory.v1beta1.RegistrationClient",
          "shortName": "RegistrationClient"
        },
        "fullName": "google.cloud.servicedirectory.v1beta1.RegistrationClient.ListEndpoints",
        "method": {
          "fullName": "google.cloud.servicedirectory.v1beta1.RegistrationService.ListEndpoints",
          "service": {
            "fullName": "google.cloud.servicedirectory.v1beta1.RegistrationService",
            "shortName": "RegistrationService"
          },
          "shortName": "ListEndpoints"
        },
        "parameters": [
          {
            "name": "ctx",
            "type": "context.Context"
          },
          {
            "name": "req",
            "type": "servicedirectorypb.ListEndpointsRequest"
          },
          {
            "name": "opts",
            "type": "...gax.CallOption"
          }
        ],
        "resultType": "EndpointIterator",
        "shortName": "ListEndpoints"
      },
      "description": "ListEndpoints lists all endpoints.",
      "file": "RegistrationClient/ListEndpoints/main.go",
      "language": "GO",
      "origin": "API_DEFINITION",
      "regionTag": "servicedirectory_v1beta1_generated_RegistrationService_ListEndpoints_sync",
      "segments": [
        {
          "end": 66,
          "start": 18,
          "type": "FULL"
        }
      ],
      "title": "servicedirectory ListEndpoints Sample"
    },
    {
      "clientMethod": {
        "client": {
          "fullName": "google.cloud.servicedirectory.v1beta1.RegistrationClient",
          "shortName": "RegistrationClient"
        },
        "fullName": "google.cloud.servicedirectory.v1beta1.RegistrationClient.ListLocations",
        "method": {
          "fullName": "google.cloud.location.Locations.ListLocations",
          "service": {
            "fullName": "google.cloud.location.Locations",
            "shortName": "Locations"
          },
          "shortName": "ListLocations"
        },
        "parameters": [
          {
            "name": "ctx",
            "type": "context.Context"
          },
          {
            "name": "req",
            "type": "locationpb.ListLocationsRequest"
          },
          {
            "name": "opts",
            "type": "...gax.CallOption"
          }
        ],
        "resultType": "LocationIterator",
        "shortName": "ListLocations"
      },
      "description": "ListLocations lists information about the supported locations for this service.",
      "file": "RegistrationClient/ListLocations/main.go",
      "language": "GO",
      "origin": "API_DEFINITION",
      "regionTag": "servicedirectory_v1beta1_generated_RegistrationService_ListLocations_sync",
      "segments": [
        {
          "end": 66,
          "start": 18,
          "type": "FULL"
        }
      ],
      "title": "servicedirectory ListLocations Sample"
    },
    {
      "clientMethod": {
        "client": {
          "fullName": "google.cloud.servicedirectory.v1beta1.RegistrationClient",
          "shortName": "RegistrationClient"
        },
        "fullName": "google.cloud.servicedirectory.v1beta1.RegistrationClient.ListNamespaces",
        "method": {
          "fullName": "google.cloud.servicedirectory.v1beta1.RegistrationService.ListNamespaces",
          "service": {
            "fullName": "google.cloud.servicedirectory.v1beta1.RegistrationService",
            "shortName": "RegistrationService"
          },
          "shortName": "ListNamespaces"
        },
        "parameters": [
          {
            "name": "ctx",
            "type": "context.Context"
          },
          {
            "name": "req",
            "type": "servicedirectorypb.ListNamespacesRequest"
          },
          {
            "name": "opts",
            "type": "...gax.CallOption"
          }
        ],
        "resultType": "NamespaceIterator",
        "shortName": "ListNamespaces"
      },
      "description": "ListNamespaces lists all namespaces.",
      "file": "RegistrationClient/ListNamespaces/main.go",
      "language": "GO",
      "origin": "API_DEFINITION",
      "regionTag": "servicedirectory_v1beta1_generated_RegistrationService_ListNamespaces_sync",
      "segments": [
        {
          "end": 66,
          "start": 18,
          "type": "FULL"
        }
      ],
      "title": "servicedirectory ListNamespaces Sample"
    },
    {
      "clientMethod": {
        "client": {
          "fullName": "google.cloud.servicedirectory.v1beta1.RegistrationClient",
          "shortName": "RegistrationClient"
        },
        "fullName": "google.cloud.servicedirectory.v1beta1.RegistrationClient.ListServices",
        "method": {
          "fullName": "google.cloud.servicedirectory.v1beta1.RegistrationService.ListServices",
          "service": {
            "fullName": "google.cloud.servicedirectory.v1beta1.RegistrationService",
            "shortName": "RegistrationService"
          },
          "shortName": "ListServices"
        },
        "parameters": [
          {
            "name": "ctx",
            "type": "context.Context"
          },
          {
            "name": "req",
            "type": "servicedirectorypb.ListServicesRequest"
          },
          {
            "name": "opts",
            "type": "...gax.CallOption"
          }
        ],
        "resultType": "ServiceIterator",
        "shortName": "ListServices"
      },
      "description": "ListServices lists all services belonging to a namespace.",
      "file": "RegistrationClient/ListServices/main.go",
      "language": "GO",
      "origin": "API_DEFINITION",
      "regionTag": "servicedirectory_v1beta1_generated_RegistrationService_ListServices_sync",
      "segments": [
        {
          "end": 66,
          "start": 18,
          "type": "FULL"
        }
      ],
      "title": "servicedirectory ListServices Sample"
    },
    {
      "clientMethod": {
        "client": {
          "fullName": "google.cloud.servicedirectory.v1beta1.RegistrationClient",
          "shortName": "RegistrationClient"
        },
        "fullName": "google.cloud.servicedirectory.v1beta1.RegistrationClient.SetIamPolicy",
        "method": {
          "fullName": "google.cloud.servicedirectory.v1beta1.RegistrationService.SetIamPolicy",
          "service": {
            "fullName": "google.cloud.servicedirectory.v1beta1.RegistrationService",
            "shortName": "RegistrationService"
          },
          "shortName": "SetIamPolicy"
        },
        "parameters": [
          {
            "name": "ctx",
            "type": "context.Context"
          },
          {
            "name": "req",
            "type": "iampb.SetIamPolicyRequest"
          },
          {
            "name": "opts",
            "type": "...gax.CallOption"
          }
        ],
        "resultType": "*iampb.Policy",
        "shortName": "SetIamPolicy"
      },
      "description": "SetIamPolicy sets the IAM Policy for a resource",
      "file": "RegistrationClient/SetIamPolicy/main.go",
      "language": "GO",
      "origin": "API_DEFINITION",
      "regionTag": "servicedirectory_v1beta1_generated_RegistrationService_SetIamPolicy_sync",
      "segments": [
        {
          "end": 53,
          "start": 18,
          "type": "FULL"
        }
      ],
      "title": "servicedirectory SetIamPolicy Sample"
    },
    {
      "clientMethod": {
        "client": {
          "fullName": "google.cloud.servicedirectory.v1beta1.RegistrationClient",
          "shortName": "RegistrationClient"
        },
        "fullName": "google.cloud.servicedirectory.v1beta1.RegistrationClient.TestIamPermissions",
        "method": {
          "fullName": "google.cloud.servicedirectory.v1beta1.RegistrationService.TestIamPermissions",
          "service": {
            "fullName": "google.cloud.servicedirectory.v1beta1.RegistrationService",
            "shortName": "RegistrationService"
          },
          "shortName": "TestIamPermissions"
        },
        "parameters": [
          {
            "name": "ctx",
            "type": "context.Context"
          },
          {
            "name": "req",
            "type": "iampb.TestIamPermissionsRequest"
          },
          {
            "name": "opts",
            "type": "...gax.CallOption"
          }
        ],
        "resultType": "*iampb.TestIamPermissionsResponse",
        "shortName": "TestIamPermissions"
      },
      "description": "TestIamPermissions tests IAM permissions for a resource (namespace, service  or\nservice workload only).",
      "file": "RegistrationClient/TestIamPermissions/main.go",
      "language": "GO",
      "origin": "API_DEFINITION",
      "regionTag": "servicedirectory_v1beta1_generated_RegistrationService_TestIamPermissions_sync",
      "segments": [
        {
          "end": 53,
          "start": 18,
          "type": "FULL"
        }
      ],
      "title": "servicedirectory TestIamPermissions Sample"
    },
    {
      "clientMethod": {
        "client": {
          "fullName": "google.cloud.servicedirectory.v1beta1.RegistrationClient",
          "shortName": "RegistrationClient"
        },
        "fullName": "google.cloud.servicedirectory.v1beta1.RegistrationClient.UpdateEndpoint",
        "method": {
          "fullName": "google.cloud.servicedirectory.v1beta1.RegistrationService.UpdateEndpoint",
          "service": {
            "fullName": "google.cloud.servicedirectory.v1beta1.RegistrationService",
            "shortName": "RegistrationService"
          },
          "shortName": "UpdateEndpoint"
        },
        "parameters": [
          {
            "name": "ctx",
            "type": "context.Context"
          },
          {
            "name": "req",
            "type": "servicedirectorypb.UpdateEndpointRequest"
          },
          {
            "name": "opts",
            "type": "...gax.CallOption"
          }
        ],
        "resultType": "*servicedirectorypb.Endpoint",
        "shortName": "UpdateEndpoint"
      },
      "description": "UpdateEndpoint updates an endpoint.",
      "file": "RegistrationClient/UpdateEndpoint/main.go",
      "language": "GO",
      "origin": "API_DEFINITION",
      "regionTag": "servicedirectory_v1beta1_generated_RegistrationService_UpdateEndpoint_sync",
      "segments": [
        {
          "end": 53,
          "start": 18,
          "type": "FULL"
        }
      ],
      "title": "servicedirectory UpdateEndpoint Sample"
    },
    {
      "clientMethod": {
        "client": {
          "fullName": "google.cloud.servicedirectory.v1beta1.RegistrationClient",
          "shortName": "RegistrationClient"
        },
        "fullName": "google.cloud.servicedirectory.v1beta1.RegistrationClient.UpdateNamespace",
        "method": {
          "fullName": "google.cloud.servicedirectory.v1beta1.RegistrationService.UpdateNamespace",
          "service": {
            "fullName": "google.cloud.servicedirectory.v1beta1.RegistrationService",
            "shortName": "RegistrationService"
          },
          "shortName": "UpdateNamespace"
        },
        "parameters": [
          {
            "name": "ctx",
            "type": "context.Context"
          },
          {
            "name": "req",
            "type": "servicedirectorypb.UpdateNamespaceRequest"
          },
          {
            "name": "opts",
            "type": "...gax.CallOption"
          }
        ],
        "resultType": "*servicedirectorypb.Namespace",
        "shortName": "UpdateNamespace"
      },
      "description": "UpdateNamespace updates a namespace.",
      "file": "RegistrationClient/UpdateNamespace/main.go",
      "language": "GO",
      "origin": "API_DEFINITION",
      "regionTag": "servicedirectory_v1beta1_generated_RegistrationService_UpdateNamespace_sync",
      "segments": [
        {
          "end": 53,
          "start": 18,
          "type": "FULL"
        }
      ],
      "title": "servicedirectory UpdateNamespace Sample"
    },
    {
      "clientMethod": {
        "client": {
          "fullName": "google.cloud.servicedirectory.v1beta1.RegistrationClient",
          "shortName": "RegistrationClient"
        },
        "fullName": "google.cloud.servicedirectory.v1beta1.RegistrationClient.UpdateService",
        "method": {
          "fullName": "google.cloud.servicedirectory.v1beta1.RegistrationService.UpdateService",
          "service": {
            "fullName": "google.cloud.servicedirectory.v1beta1.RegistrationService",
            "shortName": "RegistrationService"
          },
          "shortName": "UpdateService"
        },
        "parameters": [
          {
            "name": "ctx",
            "type": "context.Context"
          },
          {
            "name": "req",
            "type": "servicedirectorypb.UpdateServiceRequest"
          },
          {
            "name": "opts",
            "type": "...gax.CallOption"
          }
        ],
        "resultType": "*servicedirectorypb.Service",
        "shortName": "UpdateService"
      },
      "description": "UpdateService updates a service.",
      "file": "RegistrationClient/UpdateService/main.go",
      "language": "GO",
      "origin": "API_DEFINITION",
      "regionTag": "servicedirectory_v1beta1_generated_RegistrationService_UpdateService_sync",
      "segments": [
        {
          "end": 53,
          "start": 18,
          "type": "FULL"
        }
      ],
      "title": "servicedirectory UpdateService Sample"
    }
  ]
}